ClearIO/IClearIO.py
ClearIO/LocalClearIO.py
ClearIO/S3ClearIO.py
ClearIO/SFTPClearIO.py
ClearIO/SMBClearIO.py
ClearIO/TimestampedPath.py
ClearIO/TypedPath.py
ClearIO/__init__.py
cleario-2.0.0.dist-info/METADATA
cleario-2.0.0.dist-info/WHEEL
cleario-2.0.0.dist-info/licenses/LICENSE
cleario-2.0.0.dist-info/RECORD
