Metadata-Version: 2.4
Name: ClearIO
Version: 2.0.0
Summary: Utility library for accessing IO providers in a uniform way.
Project-URL: Homepage, https://github.com/bradleydonmorris/ClearIO
Project-URL: Issues, https://github.com/bradleydonmorris/ClearIO/issues
Author-email: Bradley Morris <bradleydonmorris@hotmail.com>
License-File: LICENSE
Classifier: License :: OSI Approved :: MIT License
Classifier: Operating System :: OS Independent
Classifier: Programming Language :: Python :: 3
Requires-Python: >=3.11
